README.md
setup.py
bestvarspk/General_variables.py
bestvarspk/Variables_selection.py
bestvarspk/__init__.py
bestvarspk.egg-info/PKG-INFO
bestvarspk.egg-info/SOURCES.txt
bestvarspk.egg-info/dependency_links.txt
bestvarspk.egg-info/not-zip-safe
bestvarspk.egg-info/top_level.txt