Metadata-Version: 2.1
Name: bestvarspk
Version: 0.3
Summary: Bestvars feature_selection methods
Home-page: UNKNOWN
Author: Gutelvam Rodrigues de Jesus
Author-email: gutto.rdj@gmail.com
License: UNKNOWN
Platform: UNKNOWN
